botty/__init__.py
botty/buttons/__init__.py
botty/buttons/callback.py
botty/buttons/url.py
botty/contexts/__init__.py
botty/contexts/message.py
botty/contexts/query.py
botty/contexts/text.py
botty/contexts/update.py
botty/handlers/__init__.py
botty/handlers/command.py
botty/handlers/inline_menu.py
botty/handlers/message.py
botty/handlers/query.py
botty/handlers/start.py
botty/handlers/text.py
botty/keyboards/__init__.py
botty/keyboards/inline.py
botty/keyboards/reply.py
botty/loader.py
botty/py.typed
botty_core/__init__.py
botty_core/app.py
botty_core/composite_handler.py
botty_core/context.py
botty_core/env.py
botty_core/handler.py
botty_core/helpers.py
botty_core/ptb_types.py
botty_core/py.typed
botty_core/texts.py
botty_core/types/__init__.py
botty_core/types/bot.py
botty_core/types/chat.py
botty_core/types/message.py
botty_core/types/object.py
botty_core/types/query.py
botty_core/types/update.py
botty_core/types/user.py
telegram_botty-0.3.23.dist-info/WHEEL
telegram_botty-0.3.23.dist-info/METADATA
telegram_botty-0.3.23.dist-info/RECORD
