Metadata-Version: 2.1
Name: telegram-botty
Version: 0.3.23
License: MIT
Author-email: levch <levchenko.d.a1998@gmail.com>
Requires-Python: >=3.11
Requires-Dist: python-telegram-bot>=20.1
